stratum/__init__.py
stratum/_rust_backend.py
stratum/_rust_backend_native.pyd
stratum/adapters/string_encoder.py
stratum/config.py
stratum/tests/__init__.py
stratum/tests/test_rust_hashing_tfidf.py
stratum/tests/test_string_encoder.py
stratum_ai-0.0.0.dev0.dist-info/METADATA
stratum_ai-0.0.0.dev0.dist-info/WHEEL
stratum_ai-0.0.0.dev0.dist-info/licenses/LICENSE.txt
stratum_ai-0.0.0.dev0.dist-info/RECORD
