Metadata-Version: 2.4
Name: stratum-ai
Version: 0.0.0.dev0
Classifier: Development Status :: 4 - Beta
Classifier: Environment :: Console
Classifier: Intended Audience :: Science/Research
Classifier: License :: OSI Approved :: BSD License
Classifier: Operating System :: OS Independent
Classifier: Programming Language :: Python :: 3.10
Classifier: Programming Language :: Python :: 3.11
Classifier: Programming Language :: Python :: 3.12
Classifier: Programming Language :: Python :: 3.13
Classifier: Topic :: Scientific/Engineering
Classifier: Topic :: Software Development :: Libraries
Requires-Dist: skrub>=0.3
License-File: LICENSE.txt
Summary: skrub with a Rust backend
Author: Arnab Phani
License: BSD-3-Clause
Requires-Python: >=3.10
Project-URL: Homepage, https://github.com/deem-data/stratum
Project-URL: Issues, https://github.com/deem-data/stratum/issues
